Collecting/PagesCollector.py
Collecting/__init__.py
Collecting/collecting_logger.py
DataModels/ChapterModel.py
DataModels/MangaModel.py
DataModels/ModelsFactory.py
DataModels/PageModel.py
DataModels/__init__.py
DataModels/models_logger.py
Downloading/MangadexDownloader.py
Downloading/__init__.py
MangadexDownloaderLib/ChapterModel.py
MangadexDownloaderLib/Event.py
MangadexDownloaderLib/MangaModel.py
MangadexDownloaderLib/MangadexDownloader.py
MangadexDownloaderLib/MangadexImageParser.py
MangadexDownloaderLib/MangadexJsonParser.py
MangadexDownloaderLib/ModelsFactory.py
MangadexDownloaderLib/Observer.py
MangadexDownloaderLib/PageModel.py
MangadexDownloaderLib/PagesCollector.py
MangadexDownloaderLib/ProgressEvent.py
MangadexDownloaderLib/__init__.py
MangadexDownloaderLib/collecting_logger.py
MangadexDownloaderLib/models_logger.py
MangadexDownloaderLib/parsing_logger.py
Notifying/Event.py
Notifying/Observer.py
Notifying/ProgressEvent.py
Notifying/__init__.py
Parsing/MangadexImageParser.py
Parsing/MangadexJsonParser.py
Parsing/__init__.py
Parsing/parsing_logger.py
MangadexDownloaderLib-1.0.1.dist-info/LICENSE
MangadexDownloaderLib-1.0.1.dist-info/METADATA
MangadexDownloaderLib-1.0.1.dist-info/WHEEL
MangadexDownloaderLib-1.0.1.dist-info/top_level.txt
MangadexDownloaderLib-1.0.1.dist-info/RECORD
